lasio/__init__.py
lasio/convert_version.py
lasio/defaults.py
lasio/examples.py
lasio/excel.py
lasio/exceptions.py
lasio/las.py
lasio/las_items.py
lasio/las_version.py
lasio/reader.py
lasio/writer.py
lasio-0.31.dist-info/LICENSE
lasio-0.31.dist-info/METADATA
lasio-0.31.dist-info/WHEEL
lasio-0.31.dist-info/entry_points.txt
lasio-0.31.dist-info/top_level.txt
lasio-0.31.dist-info/RECORD
