Metadata-Version: 2.1
Name: lasio
Version: 0.31
Summary: Read/write well data from Log ASCII Standard (LAS) files
Home-page: https://github.com/kinverarity1/lasio
Author: Kent Inverarity
Author-email: kinverarity@hotmail.com
License: MIT
Keywords: science geophysics io
Classifier: Development Status :: 4 - Beta
Classifier: Environment :: Console
Classifier: Intended Audience :: Customer Service
Classifier: Intended Audience :: Developers
Classifier: Intended Audience :: Education
Classifier: Intended Audience :: End Users/Desktop
Classifier: Intended Audience :: Other Audience
Classifier: Intended Audience :: Science/Research
Classifier: License :: OSI Approved :: MIT License
Classifier: Natural Language :: English
Classifier: Operating System :: OS Independent
Classifier: Programming Language :: Python :: 3
Classifier: Programming Language :: Python :: 3.7
Classifier: Programming Language :: Python :: 3.8
Classifier: Programming Language :: Python :: 3.9
Classifier: Programming Language :: Python :: 3.10
Classifier: Programming Language :: Python :: 3.11
Classifier: Topic :: Scientific/Engineering
Classifier: Topic :: System :: Filesystems
Classifier: Topic :: Scientific/Engineering :: Information Analysis
Requires-Python: >=3
License-File: LICENSE
Requires-Dist: numpy
Provides-Extra: all
Requires-Dist: pandas ; extra == 'all'
Requires-Dist: chardet ; extra == 'all'
Requires-Dist: openpyxl ; extra == 'all'
Provides-Extra: test
Requires-Dist: pandas ; extra == 'test'
Requires-Dist: chardet ; extra == 'test'
Requires-Dist: openpyxl ; extra == 'test'
Requires-Dist: pytest (>=3.6) ; extra == 'test'
Requires-Dist: pytest-cov ; extra == 'test'
Requires-Dist: coverage ; extra == 'test'
Requires-Dist: codecov ; extra == 'test'
Requires-Dist: pytest-benchmark ; extra == 'test'
Requires-Dist: black ; extra == 'test'
